JcMailText/__init__.py
JcMailText-0.0.6.dist-info/METADATA
JcMailText-0.0.6.dist-info/WHEEL
JcMailText-0.0.6.dist-info/top_level.txt
JcMailText-0.0.6.dist-info/RECORD
