Metadata-Version: 2.1
Name: JcMailText
Version: 0.0.6
Summary: Mail Text library by JavaCommons Technologies
Home-page: https://github.com/javacommons/py-mail-text
Author: JavaCommons Technologies
Author-email: javacommmons@gmail.com
License: MIT
Requires-Dist: bs4
